crypto_news_api/__init__.py
crypto_news_api-2.3.1.dist-info/METADATA
crypto_news_api-2.3.1.dist-info/RECORD
crypto_news_api-2.3.1.dist-info/WHEEL
crypto_news_api-2.3.1.dist-info/top_level.txt
