Metadata-Version: 2.1
Name: crypto-news-api
Version: 2.3.1
Summary: Client to get a crypto newsfeed in your app from the CryptoControl API
Home-page: https://github.com/cryptocontrol/python-api
Author: Steven Enamakel
Author-email: enamakel@cryptocontrol.io
License: UNKNOWN
Download-URL: https://github.com/cryptocontrol/python-api/archive/2.2.0.tar.gz
Keywords: crypto,news,cryptocurrency,blockchain,api
Platform: UNKNOWN
